madan/__int__.py
madan/cv/README.md
madan/cv/__init__.py
madan/cv/inference.py
madan/inference.py
madan/math/.gitignore
madan/ml/.gitignore
madan/nlp/.gitignore
madan-0.1.0.dist-info/WHEEL
madan-0.1.0.dist-info/METADATA
madan-0.1.0.dist-info/RECORD
