Metadata-Version: 2.1
Name: madan
Version: 0.1.0
Summary: Open source ai library
Home-page: https://github.com/MadanBaduwal/madan
Keywords: math,machine learning,computer vision,natural language processing,madan
Author: MadanBaduwal
Author-email: madanbaduwal100@gmail.com
Requires-Python: >=3.8,<4.0
Classifier: Programming Language :: Python :: 3
Classifier: Programming Language :: Python :: 3.8
Classifier: Programming Language :: Python :: 3.9
Classifier: Programming Language :: Python :: 3.10
Requires-Dist: streamlit (>=0.84.2,<0.85.0)
Project-URL: Documentation, https://github.com/MadanBaduwal/madan/wiki
Project-URL: Repository, https://github.com/MadanBaduwal/madan
